<annotation>
	<folder>VOC2010</folder>
	<filename>2008_000488.jpg</filename>
	<source>
		<database>The VOC2008 Database</database>
		<annotation>PASCAL VOC2008</annotation>
		<image>flickr</image>
	</source>
	<size>
		<width>500</width>
		<height>375</height>
		<depth>3</depth>
	</size>
	<segmented>0</segmented>
	<object>
		<name>car</name>
		<pose>Left</pose>
		<truncated>0</truncated>
		<occluded>0</occluded>
		<bndbox>
			<xmin>307</xmin>
			<ymin>287</ymin>
			<xmax>486</xmax>
			<ymax>347</ymax>
		</bndbox>
		<difficult>0</difficult>
	</object>
	<object>
		<name>pottedplant</name>
		<pose>Unspecified</pose>
		<truncated>0</truncated>
		<occluded>0</occluded>
		<bndbox>
			<xmin>44</xmin>
			<ymin>288</ymin>
			<xmax>61</xmax>
			<ymax>304</ymax>
		</bndbox>
		<difficult>1</difficult>
	</object>
	<object>
		<name>pottedplant</name>
		<pose>Unspecified</pose>
		<truncated>0</truncated>
		<occluded>1</occluded>
		<bndbox>
			<xmin>25</xmin>
			<ymin>284</ymin>
			<xmax>37</xmax>
			<ymax>306</ymax>
		</bndbox>
		<difficult>1</difficult>
	</object>
</annotation>
