<annotation>
	<folder>VOC2010</folder>
	<filename>2008_007595.jpg</filename>
	<source>
		<database>The VOC2008 Database</database>
		<annotation>PASCAL VOC2008</annotation>
		<image>flickr</image>
	</source>
	<size>
		<width>375</width>
		<height>500</height>
		<depth>3</depth>
	</size>
	<segmented>0</segmented>
	<object>
		<name>car</name>
		<pose>Rear</pose>
		<truncated>1</truncated>
		<occluded>1</occluded>
		<bndbox>
			<xmin>213</xmin>
			<ymin>322</ymin>
			<xmax>227</xmax>
			<ymax>357</ymax>
		</bndbox>
		<difficult>1</difficult>
	</object>
	<object>
		<name>car</name>
		<pose>Rear</pose>
		<truncated>1</truncated>
		<occluded>1</occluded>
		<bndbox>
			<xmin>221</xmin>
			<ymin>312</ymin>
			<xmax>236</xmax>
			<ymax>362</ymax>
		</bndbox>
		<difficult>1</difficult>
	</object>
	<object>
		<name>car</name>
		<pose>Rear</pose>
		<truncated>1</truncated>
		<occluded>1</occluded>
		<bndbox>
			<xmin>226</xmin>
			<ymin>304</ymin>
			<xmax>249</xmax>
			<ymax>365</ymax>
		</bndbox>
		<difficult>1</difficult>
	</object>
	<object>
		<name>car</name>
		<pose>Rear</pose>
		<truncated>1</truncated>
		<occluded>1</occluded>
		<bndbox>
			<xmin>240</xmin>
			<ymin>250</ymin>
			<xmax>329</xmax>
			<ymax>382</ymax>
		</bndbox>
		<difficult>0</difficult>
	</object>
	<object>
		<name>car</name>
		<pose>Rear</pose>
		<truncated>1</truncated>
		<occluded>1</occluded>
		<bndbox>
			<xmin>258</xmin>
			<ymin>271</ymin>
			<xmax>342</xmax>
			<ymax>393</ymax>
		</bndbox>
		<difficult>1</difficult>
	</object>
	<object>
		<name>car</name>
		<pose>Rear</pose>
		<truncated>1</truncated>
		<occluded>0</occluded>
		<bndbox>
			<xmin>270</xmin>
			<ymin>237</ymin>
			<xmax>375</xmax>
			<ymax>411</ymax>
		</bndbox>
		<difficult>0</difficult>
	</object>
	<object>
		<name>car</name>
		<pose>Frontal</pose>
		<truncated>0</truncated>
		<occluded>0</occluded>
		<bndbox>
			<xmin>93</xmin>
			<ymin>333</ymin>
			<xmax>127</xmax>
			<ymax>360</ymax>
		</bndbox>
		<difficult>0</difficult>
	</object>
</annotation>
