<annotation>
	<folder>VOC2010</folder>
	<filename>2008_001697.jpg</filename>
	<source>
		<database>The VOC2008 Database</database>
		<annotation>PASCAL VOC2008</annotation>
		<image>flickr</image>
	</source>
	<size>
		<width>500</width>
		<height>334</height>
		<depth>3</depth>
	</size>
	<segmented>0</segmented>
	<object>
		<name>person</name>
		<pose>Rear</pose>
		<truncated>0</truncated>
		<occluded>0</occluded>
		<bndbox>
			<xmin>192</xmin>
			<ymin>201</ymin>
			<xmax>226</xmax>
			<ymax>310</ymax>
		</bndbox>
		<difficult>0</difficult>
	</object>
	<object>
		<name>person</name>
		<pose>Frontal</pose>
		<truncated>0</truncated>
		<occluded>0</occluded>
		<bndbox>
			<xmin>255</xmin>
			<ymin>203</ymin>
			<xmax>288</xmax>
			<ymax>319</ymax>
		</bndbox>
		<difficult>0</difficult>
	</object>
	<object>
		<name>person</name>
		<pose>Frontal</pose>
		<truncated>0</truncated>
		<occluded>0</occluded>
		<bndbox>
			<xmin>335</xmin>
			<ymin>208</ymin>
			<xmax>361</xmax>
			<ymax>274</ymax>
		</bndbox>
		<difficult>0</difficult>
	</object>
	<object>
		<name>person</name>
		<pose>Rear</pose>
		<truncated>0</truncated>
		<occluded>0</occluded>
		<bndbox>
			<xmin>288</xmin>
			<ymin>204</ymin>
			<xmax>325</xmax>
			<ymax>298</ymax>
		</bndbox>
		<difficult>0</difficult>
	</object>
	<object>
		<name>person</name>
		<pose>Rear</pose>
		<truncated>0</truncated>
		<occluded>0</occluded>
		<bndbox>
			<xmin>438</xmin>
			<ymin>186</ymin>
			<xmax>487</xmax>
			<ymax>317</ymax>
		</bndbox>
		<difficult>0</difficult>
	</object>
</annotation>
