<annotation>
	<filename>2009_000811.jpg</filename>
	<folder>VOC2010</folder>
	<object>
		<name>diningtable</name>
		<bndbox>
			<xmax>401</xmax>
			<xmin>103</xmin>
			<ymax>375</ymax>
			<ymin>67</ymin>
		</bndbox>
		<difficult>0</difficult>
		<occluded>0</occluded>
		<pose>Unspecified</pose>
		<truncated>0</truncated>
	</object>
	<object>
		<name>chair</name>
		<bndbox>
			<xmax>486</xmax>
			<xmin>306</xmin>
			<ymax>350</ymax>
			<ymin>124</ymin>
		</bndbox>
		<difficult>0</difficult>
		<occluded>1</occluded>
		<pose>Left</pose>
		<truncated>0</truncated>
	</object>
	<object>
		<name>chair</name>
		<bndbox>
			<xmax>200</xmax>
			<xmin>29</xmin>
			<ymax>354</ymax>
			<ymin>137</ymin>
		</bndbox>
		<difficult>0</difficult>
		<occluded>1</occluded>
		<pose>Right</pose>
		<truncated>0</truncated>
	</object>
	<object>
		<name>chair</name>
		<bndbox>
			<xmax>432</xmax>
			<xmin>299</xmin>
			<ymax>267</ymax>
			<ymin>87</ymin>
		</bndbox>
		<difficult>0</difficult>
		<occluded>1</occluded>
		<pose>Left</pose>
		<truncated>0</truncated>
	</object>
	<object>
		<name>chair</name>
		<bndbox>
			<xmax>397</xmax>
			<xmin>336</xmin>
			<ymax>143</ymax>
			<ymin>58</ymin>
		</bndbox>
		<difficult>0</difficult>
		<occluded>1</occluded>
		<pose>Left</pose>
		<truncated>1</truncated>
	</object>
	<object>
		<name>chair</name>
		<bndbox>
			<xmax>135</xmax>
			<xmin>58</xmin>
			<ymax>193</ymax>
			<ymin>92</ymin>
		</bndbox>
		<difficult>0</difficult>
		<occluded>1</occluded>
		<pose>Right</pose>
		<truncated>1</truncated>
	</object>
	<object>
		<name>chair</name>
		<bndbox>
			<xmax>148</xmax>
			<xmin>81</xmin>
			<ymax>147</ymax>
			<ymin>62</ymin>
		</bndbox>
		<difficult>0</difficult>
		<occluded>1</occluded>
		<pose>Right</pose>
		<truncated>1</truncated>
	</object>
	<object>
		<name>chair</name>
		<bndbox>
			<xmax>55</xmax>
			<xmin>1</xmin>
			<ymax>101</ymax>
			<ymin>21</ymin>
		</bndbox>
		<difficult>0</difficult>
		<occluded>0</occluded>
		<pose>Left</pose>
		<truncated>1</truncated>
	</object>
	<object>
		<name>chair</name>
		<bndbox>
			<xmax>69</xmax>
			<xmin>33</xmin>
			<ymax>75</ymax>
			<ymin>11</ymin>
		</bndbox>
		<difficult>0</difficult>
		<occluded>1</occluded>
		<pose>Left</pose>
		<truncated>1</truncated>
	</object>
	<segmented>0</segmented>
	<size>
		<depth>3</depth>
		<height>375</height>
		<width>500</width>
	</size>
	<source>
		<annotation>PASCAL VOC2009</annotation>
		<database>The VOC2009 Database</database>
		<image>flickr</image>
	</source>
</annotation>
