<annotation>
	<filename>2009_002784.jpg</filename>
	<folder>VOC2010</folder>
	<object>
		<name>motorbike</name>
		<bndbox>
			<xmax>376</xmax>
			<xmin>141</xmin>
			<ymax>285</ymax>
			<ymin>82</ymin>
		</bndbox>
		<difficult>0</difficult>
		<occluded>1</occluded>
		<pose>Left</pose>
		<truncated>0</truncated>
	</object>
	<object>
		<name>dog</name>
		<bndbox>
			<xmax>282</xmax>
			<xmin>239</xmin>
			<ymax>158</ymax>
			<ymin>53</ymin>
		</bndbox>
		<difficult>0</difficult>
		<occluded>1</occluded>
		<pose>Frontal</pose>
		<truncated>0</truncated>
	</object>
	<object>
		<name>person</name>
		<bndbox>
			<xmax>324</xmax>
			<xmin>204</xmin>
			<ymax>242</ymax>
			<ymin>11</ymin>
		</bndbox>
		<difficult>0</difficult>
		<occluded>0</occluded>
		<pose>Left</pose>
		<truncated>0</truncated>
	</object>
	<object>
		<name>car</name>
		<bndbox>
			<xmax>500</xmax>
			<xmin>301</xmin>
			<ymax>164</ymax>
			<ymin>34</ymin>
		</bndbox>
		<difficult>0</difficult>
		<occluded>1</occluded>
		<pose>Right</pose>
		<truncated>1</truncated>
	</object>
	<segmented>0</segmented>
	<size>
		<depth>3</depth>
		<height>333</height>
		<width>500</width>
	</size>
	<source>
		<annotation>PASCAL VOC2009</annotation>
		<database>The VOC2009 Database</database>
		<image>flickr</image>
	</source>
</annotation>
