<annotation>
	<filename>2009_000926.jpg</filename>
	<folder>VOC2010</folder>
	<object>
		<name>sofa</name>
		<bndbox>
			<xmax>500</xmax>
			<xmin>372</xmin>
			<ymax>375</ymax>
			<ymin>216</ymin>
		</bndbox>
		<difficult>0</difficult>
		<occluded>0</occluded>
		<pose>Left</pose>
		<truncated>1</truncated>
	</object>
	<object>
		<name>pottedplant</name>
		<bndbox>
			<xmax>305</xmax>
			<xmin>246</xmin>
			<ymax>248</ymax>
			<ymin>206</ymin>
		</bndbox>
		<difficult>0</difficult>
		<occluded>1</occluded>
		<pose>Unspecified</pose>
		<truncated>1</truncated>
	</object>
	<object>
		<name>pottedplant</name>
		<bndbox>
			<xmax>319</xmax>
			<xmin>258</xmin>
			<ymax>181</ymax>
			<ymin>111</ymin>
		</bndbox>
		<difficult>0</difficult>
		<occluded>1</occluded>
		<pose>Unspecified</pose>
		<truncated>1</truncated>
	</object>
	<object>
		<name>pottedplant</name>
		<bndbox>
			<xmax>483</xmax>
			<xmin>427</xmin>
			<ymax>209</ymax>
			<ymin>165</ymin>
		</bndbox>
		<difficult>0</difficult>
		<occluded>1</occluded>
		<pose>Unspecified</pose>
		<truncated>0</truncated>
	</object>
	<object>
		<name>pottedplant</name>
		<bndbox>
			<xmax>379</xmax>
			<xmin>354</xmin>
			<ymax>195</ymax>
			<ymin>165</ymin>
		</bndbox>
		<difficult>0</difficult>
		<occluded>0</occluded>
		<pose>Unspecified</pose>
		<truncated>0</truncated>
	</object>
	<object>
		<name>pottedplant</name>
		<bndbox>
			<xmax>437</xmax>
			<xmin>380</xmin>
			<ymax>168</ymax>
			<ymin>120</ymin>
		</bndbox>
		<difficult>0</difficult>
		<occluded>1</occluded>
		<pose>Unspecified</pose>
		<truncated>0</truncated>
	</object>
	<segmented>0</segmented>
	<size>
		<depth>3</depth>
		<height>375</height>
		<width>500</width>
	</size>
	<source>
		<annotation>PASCAL VOC2009</annotation>
		<database>The VOC2009 Database</database>
		<image>flickr</image>
	</source>
</annotation>
