<annotation>
	<filename>2009_004592.jpg</filename>
	<folder>VOC2010</folder>
	<object>
		<name>dog</name>
		<bndbox>
			<xmax>232</xmax>
			<xmin>75</xmin>
			<ymax>374</ymax>
			<ymin>234</ymin>
		</bndbox>
		<difficult>0</difficult>
		<occluded>0</occluded>
		<pose>Unspecified</pose>
		<truncated>0</truncated>
	</object>
	<segmented>1</segmented>
	<size>
		<depth>3</depth>
		<height>500</height>
		<width>333</width>
	</size>
	<source>
		<annotation>PASCAL VOC2009</annotation>
		<database>The VOC2009 Database</database>
		<image>flickr</image>
	</source>
</annotation>
