<annotation>
	<filename>2010_004946.jpg</filename>
	<folder>VOC2010</folder>
	<object>
		<name>car</name>
		<bndbox>
			<xmax>331</xmax>
			<xmin>37</xmin>
			<ymax>423</ymax>
			<ymin>165</ymin>
		</bndbox>
		<difficult>0</difficult>
		<occluded>0</occluded>
		<pose>Rear</pose>
		<truncated>0</truncated>
	</object>
	<segmented>1</segmented>
	<size>
		<depth>3</depth>
		<height>500</height>
		<width>375</width>
	</size>
	<source>
		<annotation>PASCAL VOC2010</annotation>
		<database>The VOC2010 Database</database>
		<image>flickr</image>
	</source>
</annotation>
