<annotation>
	<filename>2010_001453.jpg</filename>
	<folder>VOC2010</folder>
	<object>
		<name>bus</name>
		<bndbox>
			<xmax>360</xmax>
			<xmin>102</xmin>
			<ymax>252</ymax>
			<ymin>66</ymin>
		</bndbox>
		<difficult>0</difficult>
		<occluded>0</occluded>
		<pose>Unspecified</pose>
		<truncated>0</truncated>
	</object>
	<object>
		<name>car</name>
		<bndbox>
			<xmax>38</xmax>
			<xmin>1</xmin>
			<ymax>210</ymax>
			<ymin>182</ymin>
		</bndbox>
		<difficult>0</difficult>
		<occluded>0</occluded>
		<pose>Frontal</pose>
		<truncated>1</truncated>
	</object>
	<object>
		<name>person</name>
		<bndbox>
			<xmax>438</xmax>
			<xmin>401</xmin>
			<ymax>257</ymax>
			<ymin>202</ymin>
		</bndbox>
		<difficult>0</difficult>
		<occluded>0</occluded>
		<pose>Unspecified</pose>
		<truncated>0</truncated>
	</object>
	<object>
		<name>person</name>
		<bndbox>
			<xmax>58</xmax>
			<xmin>45</xmin>
			<ymax>216</ymax>
			<ymin>179</ymin>
		</bndbox>
		<difficult>0</difficult>
		<occluded>0</occluded>
		<pose>Rear</pose>
		<truncated>0</truncated>
	</object>
	<object>
		<name>person</name>
		<bndbox>
			<xmax>71</xmax>
			<xmin>57</xmin>
			<ymax>216</ymax>
			<ymin>182</ymin>
		</bndbox>
		<difficult>1</difficult>
		<occluded>0</occluded>
		<pose>Rear</pose>
		<truncated>0</truncated>
	</object>
	<segmented>0</segmented>
	<size>
		<depth>3</depth>
		<height>333</height>
		<width>500</width>
	</size>
	<source>
		<annotation>PASCAL VOC2010</annotation>
		<database>The VOC2010 Database</database>
		<image>flickr</image>
	</source>
</annotation>
