<annotation>
	<filename>2010_005466.jpg</filename>
	<folder>VOC2010</folder>
	<object>
		<name>sheep</name>
		<bndbox>
			<xmax>500</xmax>
			<xmin>451</xmin>
			<ymax>310</ymax>
			<ymin>187</ymin>
		</bndbox>
		<difficult>1</difficult>
		<occluded>0</occluded>
		<pose>Right</pose>
		<truncated>1</truncated>
	</object>
	<object>
		<name>sheep</name>
		<bndbox>
			<xmax>500</xmax>
			<xmin>391</xmin>
			<ymax>220</ymax>
			<ymin>140</ymin>
		</bndbox>
		<difficult>0</difficult>
		<occluded>0</occluded>
		<pose>Right</pose>
		<truncated>0</truncated>
	</object>
	<object>
		<name>sheep</name>
		<bndbox>
			<xmax>330</xmax>
			<xmin>248</xmin>
			<ymax>255</ymax>
			<ymin>185</ymin>
		</bndbox>
		<difficult>0</difficult>
		<occluded>0</occluded>
		<pose>Right</pose>
		<truncated>0</truncated>
	</object>
	<object>
		<name>sheep</name>
		<bndbox>
			<xmax>441</xmax>
			<xmin>391</xmin>
			<ymax>172</ymax>
			<ymin>129</ymin>
		</bndbox>
		<difficult>1</difficult>
		<occluded>1</occluded>
		<pose>Right</pose>
		<truncated>1</truncated>
	</object>
	<object>
		<name>person</name>
		<bndbox>
			<xmax>267</xmax>
			<xmin>193</xmin>
			<ymax>242</ymax>
			<ymin>119</ymin>
		</bndbox>
		<difficult>0</difficult>
		<occluded>1</occluded>
		<pose>Right</pose>
		<truncated>0</truncated>
	</object>
	<object>
		<name>person</name>
		<bndbox>
			<xmax>292</xmax>
			<xmin>250</xmin>
			<ymax>132</ymax>
			<ymin>31</ymin>
		</bndbox>
		<difficult>0</difficult>
		<occluded>0</occluded>
		<pose>Right</pose>
		<truncated>0</truncated>
	</object>
	<object>
		<name>person</name>
		<bndbox>
			<xmax>249</xmax>
			<xmin>218</xmin>
			<ymax>135</ymax>
			<ymin>35</ymin>
		</bndbox>
		<difficult>0</difficult>
		<occluded>0</occluded>
		<pose>Right</pose>
		<truncated>0</truncated>
	</object>
	<segmented>0</segmented>
	<size>
		<depth>3</depth>
		<height>374</height>
		<width>500</width>
	</size>
	<source>
		<annotation>PASCAL VOC2010</annotation>
		<database>The VOC2010 Database</database>
		<image>flickr</image>
	</source>
</annotation>
