<annotation>
	<filename>2010_004225.jpg</filename>
	<folder>VOC2010</folder>
	<object>
		<name>sheep</name>
		<bndbox>
			<xmax>375</xmax>
			<xmin>169</xmin>
			<ymax>377</ymax>
			<ymin>262</ymin>
		</bndbox>
		<difficult>0</difficult>
		<occluded>0</occluded>
		<pose>Unspecified</pose>
		<truncated>0</truncated>
	</object>
	<object>
		<name>sheep</name>
		<bndbox>
			<xmax>339</xmax>
			<xmin>216</xmin>
			<ymax>142</ymax>
			<ymin>18</ymin>
		</bndbox>
		<difficult>0</difficult>
		<occluded>1</occluded>
		<pose>Unspecified</pose>
		<truncated>1</truncated>
	</object>
	<object>
		<name>person</name>
		<bndbox>
			<xmax>305</xmax>
			<xmin>193</xmin>
			<ymax>278</ymax>
			<ymin>87</ymin>
		</bndbox>
		<difficult>0</difficult>
		<occluded>1</occluded>
		<pose>Frontal</pose>
		<truncated>1</truncated>
	</object>
	<object>
		<name>person</name>
		<bndbox>
			<xmax>37</xmax>
			<xmin>1</xmin>
			<ymax>201</ymax>
			<ymin>55</ymin>
		</bndbox>
		<difficult>1</difficult>
		<occluded>0</occluded>
		<pose>Unspecified</pose>
		<truncated>1</truncated>
	</object>
	<object>
		<name>person</name>
		<bndbox>
			<xmax>74</xmax>
			<xmin>1</xmin>
			<ymax>145</ymax>
			<ymin>1</ymin>
		</bndbox>
		<difficult>1</difficult>
		<occluded>1</occluded>
		<pose>Unspecified</pose>
		<truncated>1</truncated>
	</object>
	<object>
		<name>person</name>
		<bndbox>
			<xmax>152</xmax>
			<xmin>99</xmin>
			<ymax>71</ymax>
			<ymin>1</ymin>
		</bndbox>
		<difficult>1</difficult>
		<occluded>0</occluded>
		<pose>Unspecified</pose>
		<truncated>1</truncated>
	</object>
	<object>
		<name>person</name>
		<bndbox>
			<xmax>167</xmax>
			<xmin>98</xmin>
			<ymax>41</ymax>
			<ymin>1</ymin>
		</bndbox>
		<difficult>1</difficult>
		<occluded>1</occluded>
		<pose>Unspecified</pose>
		<truncated>1</truncated>
	</object>
	<object>
		<name>person</name>
		<bndbox>
			<xmax>241</xmax>
			<xmin>183</xmin>
			<ymax>97</ymax>
			<ymin>1</ymin>
		</bndbox>
		<difficult>1</difficult>
		<occluded>0</occluded>
		<pose>Unspecified</pose>
		<truncated>1</truncated>
	</object>
	<object>
		<name>person</name>
		<bndbox>
			<xmax>321</xmax>
			<xmin>285</xmin>
			<ymax>33</ymax>
			<ymin>1</ymin>
		</bndbox>
		<difficult>1</difficult>
		<occluded>1</occluded>
		<pose>Unspecified</pose>
		<truncated>1</truncated>
	</object>
	<object>
		<name>person</name>
		<bndbox>
			<xmax>482</xmax>
			<xmin>402</xmin>
			<ymax>204</ymax>
			<ymin>55</ymin>
		</bndbox>
		<difficult>0</difficult>
		<occluded>0</occluded>
		<pose>Unspecified</pose>
		<truncated>0</truncated>
	</object>
	<object>
		<name>person</name>
		<bndbox>
			<xmax>500</xmax>
			<xmin>364</xmin>
			<ymax>204</ymax>
			<ymin>20</ymin>
		</bndbox>
		<difficult>1</difficult>
		<occluded>1</occluded>
		<pose>Unspecified</pose>
		<truncated>1</truncated>
	</object>
	<object>
		<name>person</name>
		<bndbox>
			<xmax>500</xmax>
			<xmin>427</xmin>
			<ymax>377</ymax>
			<ymin>82</ymin>
		</bndbox>
		<difficult>1</difficult>
		<occluded>0</occluded>
		<pose>Unspecified</pose>
		<truncated>1</truncated>
	</object>
	<object>
		<name>person</name>
		<bndbox>
			<xmax>500</xmax>
			<xmin>469</xmin>
			<ymax>41</ymax>
			<ymin>1</ymin>
		</bndbox>
		<difficult>1</difficult>
		<occluded>1</occluded>
		<pose>Unspecified</pose>
		<truncated>1</truncated>
	</object>
	<segmented>0</segmented>
	<size>
		<depth>3</depth>
		<height>377</height>
		<width>500</width>
	</size>
	<source>
		<annotation>PASCAL VOC2010</annotation>
		<database>The VOC2010 Database</database>
		<image>flickr</image>
	</source>
</annotation>
