<annotation>
	<filename>2010_005985.jpg</filename>
	<folder>VOC2010</folder>
	<object>
		<name>chair</name>
		<bndbox>
			<xmax>297</xmax>
			<xmin>251</xmin>
			<ymax>374</ymax>
			<ymin>245</ymin>
		</bndbox>
		<difficult>0</difficult>
		<occluded>1</occluded>
		<pose>Unspecified</pose>
		<truncated>1</truncated>
	</object>
	<object>
		<name>chair</name>
		<bndbox>
			<xmax>277</xmax>
			<xmin>170</xmin>
			<ymax>405</ymax>
			<ymin>255</ymin>
		</bndbox>
		<difficult>0</difficult>
		<occluded>1</occluded>
		<pose>Unspecified</pose>
		<truncated>1</truncated>
	</object>
	<object>
		<name>chair</name>
		<bndbox>
			<xmax>163</xmax>
			<xmin>140</xmin>
			<ymax>267</ymax>
			<ymin>231</ymin>
		</bndbox>
		<difficult>0</difficult>
		<occluded>0</occluded>
		<pose>Unspecified</pose>
		<truncated>1</truncated>
	</object>
	<object>
		<name>chair</name>
		<bndbox>
			<xmax>140</xmax>
			<xmin>107</xmin>
			<ymax>276</ymax>
			<ymin>237</ymin>
		</bndbox>
		<difficult>0</difficult>
		<occluded>1</occluded>
		<pose>Unspecified</pose>
		<truncated>1</truncated>
	</object>
	<object>
		<name>chair</name>
		<bndbox>
			<xmax>158</xmax>
			<xmin>58</xmin>
			<ymax>399</ymax>
			<ymin>243</ymin>
		</bndbox>
		<difficult>0</difficult>
		<occluded>1</occluded>
		<pose>Unspecified</pose>
		<truncated>0</truncated>
	</object>
	<object>
		<name>chair</name>
		<bndbox>
			<xmax>250</xmax>
			<xmin>125</xmin>
			<ymax>442</ymax>
			<ymin>267</ymin>
		</bndbox>
		<difficult>0</difficult>
		<occluded>1</occluded>
		<pose>Unspecified</pose>
		<truncated>1</truncated>
	</object>
	<object>
		<name>diningtable</name>
		<bndbox>
			<xmax>296</xmax>
			<xmin>19</xmin>
			<ymax>452</ymax>
			<ymin>253</ymin>
		</bndbox>
		<difficult>0</difficult>
		<occluded>1</occluded>
		<pose>Unspecified</pose>
		<truncated>0</truncated>
	</object>
	<segmented>0</segmented>
	<size>
		<depth>3</depth>
		<height>500</height>
		<width>333</width>
	</size>
	<source>
		<annotation>PASCAL VOC2010</annotation>
		<database>The VOC2010 Database</database>
		<image>flickr</image>
	</source>
</annotation>
