<annotation>
	<filename>2010_005352.jpg</filename>
	<folder>VOC2010</folder>
	<object>
		<name>person</name>
		<bndbox>
			<xmax>164</xmax>
			<xmin>132</xmin>
			<ymax>218</ymax>
			<ymin>143</ymin>
		</bndbox>
		<difficult>0</difficult>
		<occluded>1</occluded>
		<pose>Frontal</pose>
		<truncated>1</truncated>
	</object>
	<object>
		<name>person</name>
		<bndbox>
			<xmax>190</xmax>
			<xmin>154</xmin>
			<ymax>229</ymax>
			<ymin>136</ymin>
		</bndbox>
		<difficult>0</difficult>
		<occluded>1</occluded>
		<pose>Frontal</pose>
		<truncated>1</truncated>
	</object>
	<object>
		<name>person</name>
		<bndbox>
			<xmax>222</xmax>
			<xmin>181</xmin>
			<ymax>226</ymax>
			<ymin>138</ymin>
		</bndbox>
		<difficult>0</difficult>
		<occluded>1</occluded>
		<pose>Frontal</pose>
		<truncated>1</truncated>
	</object>
	<object>
		<name>person</name>
		<bndbox>
			<xmax>248</xmax>
			<xmin>211</xmin>
			<ymax>228</ymax>
			<ymin>134</ymin>
		</bndbox>
		<difficult>0</difficult>
		<occluded>1</occluded>
		<pose>Frontal</pose>
		<truncated>1</truncated>
	</object>
	<object>
		<name>person</name>
		<bndbox>
			<xmax>278</xmax>
			<xmin>238</xmin>
			<ymax>223</ymax>
			<ymin>132</ymin>
		</bndbox>
		<difficult>0</difficult>
		<occluded>1</occluded>
		<pose>Frontal</pose>
		<truncated>1</truncated>
	</object>
	<object>
		<name>person</name>
		<bndbox>
			<xmax>302</xmax>
			<xmin>271</xmin>
			<ymax>219</ymax>
			<ymin>129</ymin>
		</bndbox>
		<difficult>0</difficult>
		<occluded>1</occluded>
		<pose>Unspecified</pose>
		<truncated>1</truncated>
	</object>
	<object>
		<name>person</name>
		<bndbox>
			<xmax>336</xmax>
			<xmin>285</xmin>
			<ymax>228</ymax>
			<ymin>132</ymin>
		</bndbox>
		<difficult>0</difficult>
		<occluded>1</occluded>
		<pose>Frontal</pose>
		<truncated>1</truncated>
	</object>
	<object>
		<name>person</name>
		<bndbox>
			<xmax>402</xmax>
			<xmin>332</xmin>
			<ymax>318</ymax>
			<ymin>111</ymin>
		</bndbox>
		<difficult>0</difficult>
		<occluded>1</occluded>
		<pose>Frontal</pose>
		<truncated>0</truncated>
		<part>
			<name>head</name>
			<bndbox>
				<xmin>340</xmin>
				<ymin>111</ymin>
				<xmax>362</xmax>
				<ymax>142</ymax>
			</bndbox>
		</part>
		<part>
			<name>hand</name>
			<bndbox>
				<xmin>361</xmin>
				<ymin>196</ymin>
				<xmax>381</xmax>
				<ymax>206</ymax>
			</bndbox>
		</part>
		<part>
			<name>foot</name>
			<bndbox>
				<xmin>337</xmin>
				<ymin>297</ymin>
				<xmax>365</xmax>
				<ymax>308</ymax>
			</bndbox>
		</part>
		<part>
			<name>foot</name>
			<bndbox>
				<xmin>374</xmin>
				<ymin>305</ymin>
				<xmax>390</xmax>
				<ymax>318</ymax>
			</bndbox>
		</part>
	</object>
	<object>
		<name>person</name>
		<bndbox>
			<xmax>356</xmax>
			<xmin>290</xmin>
			<ymax>310</ymax>
			<ymin>204</ymin>
		</bndbox>
		<difficult>0</difficult>
		<occluded>0</occluded>
		<pose>Frontal</pose>
		<truncated>0</truncated>
	</object>
	<object>
		<name>person</name>
		<bndbox>
			<xmax>315</xmax>
			<xmin>248</xmin>
			<ymax>302</ymax>
			<ymin>191</ymin>
		</bndbox>
		<difficult>0</difficult>
		<occluded>1</occluded>
		<pose>Frontal</pose>
		<truncated>0</truncated>
	</object>
	<object>
		<name>person</name>
		<bndbox>
			<xmax>267</xmax>
			<xmin>207</xmin>
			<ymax>300</ymax>
			<ymin>195</ymin>
		</bndbox>
		<difficult>0</difficult>
		<occluded>1</occluded>
		<pose>Frontal</pose>
		<truncated>0</truncated>
	</object>
	<object>
		<name>person</name>
		<bndbox>
			<xmax>229</xmax>
			<xmin>188</xmin>
			<ymax>297</ymax>
			<ymin>203</ymin>
		</bndbox>
		<difficult>0</difficult>
		<occluded>1</occluded>
		<pose>Frontal</pose>
		<truncated>0</truncated>
	</object>
	<object>
		<name>person</name>
		<bndbox>
			<xmax>202</xmax>
			<xmin>151</xmin>
			<ymax>298</ymax>
			<ymin>200</ymin>
		</bndbox>
		<difficult>0</difficult>
		<occluded>1</occluded>
		<pose>Frontal</pose>
		<truncated>0</truncated>
	</object>
	<object>
		<name>person</name>
		<bndbox>
			<xmax>171</xmax>
			<xmin>137</xmin>
			<ymax>295</ymax>
			<ymin>201</ymin>
		</bndbox>
		<difficult>0</difficult>
		<occluded>1</occluded>
		<pose>Frontal</pose>
		<truncated>0</truncated>
	</object>
	<object>
		<name>person</name>
		<bndbox>
			<xmax>148</xmax>
			<xmin>90</xmin>
			<ymax>307</ymax>
			<ymin>204</ymin>
		</bndbox>
		<difficult>0</difficult>
		<occluded>0</occluded>
		<pose>Unspecified</pose>
		<truncated>0</truncated>
	</object>
	<object>
		<name>person</name>
		<bndbox>
			<xmax>141</xmax>
			<xmin>84</xmin>
			<ymax>300</ymax>
			<ymin>132</ymin>
		</bndbox>
		<difficult>0</difficult>
		<occluded>1</occluded>
		<pose>Frontal</pose>
		<truncated>0</truncated>
		<part>
			<name>head</name>
			<bndbox>
				<xmin>108</xmin>
				<ymin>135</ymin>
				<xmax>127</xmax>
				<ymax>160</ymax>
			</bndbox>
		</part>
		<part>
			<name>hand</name>
			<bndbox>
				<xmin>98</xmin>
				<ymin>179</ymin>
				<xmax>117</xmax>
				<ymax>189</ymax>
			</bndbox>
		</part>
		<part>
			<name>hand</name>
			<bndbox>
				<xmin>108</xmin>
				<ymin>189</ymin>
				<xmax>123</xmax>
				<ymax>200</ymax>
			</bndbox>
		</part>
		<part>
			<name>foot</name>
			<bndbox>
				<xmin>83</xmin>
				<ymin>286</ymin>
				<xmax>99</xmax>
				<ymax>301</ymax>
			</bndbox>
		</part>
	</object>
	<object>
		<name>person</name>
		<bndbox>
			<xmax>424</xmax>
			<xmin>415</xmin>
			<ymax>34</ymax>
			<ymin>13</ymin>
		</bndbox>
		<difficult>0</difficult>
		<occluded>1</occluded>
		<pose>Rear</pose>
		<truncated>1</truncated>
	</object>
	<object>
		<name>person</name>
		<bndbox>
			<xmax>500</xmax>
			<xmin>492</xmin>
			<ymax>210</ymax>
			<ymin>166</ymin>
		</bndbox>
		<difficult>0</difficult>
		<occluded>0</occluded>
		<pose>Unspecified</pose>
		<truncated>1</truncated>
	</object>
	<segmented>0</segmented>
	<size>
		<depth>3</depth>
		<height>325</height>
		<width>500</width>
	</size>
	<source>
		<annotation>PASCAL VOC2010</annotation>
		<database>The VOC2010 Database</database>
		<image>flickr</image>
	</source>
</annotation>
