<annotation>
	<filename>2010_006179.jpg</filename>
	<folder>VOC2010</folder>
	<object>
		<name>person</name>
		<bndbox>
			<xmax>179</xmax>
			<xmin>65</xmin>
			<ymax>339</ymax>
			<ymin>12</ymin>
		</bndbox>
		<difficult>0</difficult>
		<pose>Unspecified</pose>
		<actions>
			<phoning>0</phoning>
			<playinginstrument>0</playinginstrument>
			<reading>0</reading>
			<ridingbike>0</ridingbike>
			<ridinghorse>0</ridinghorse>
			<running>1</running>
			<takingphoto>0</takingphoto>
			<usingcomputer>0</usingcomputer>
			<walking>0</walking>
		</actions>
	</object>
	<segmented>0</segmented>
	<size>
		<depth>3</depth>
		<height>382</height>
		<width>257</width>
	</size>
	<source>
		<annotation>PASCAL VOC2010</annotation>
		<database>The VOC2010 Database</database>
		<image>flickr</image>
	</source>
</annotation>
